{
  "source": "https://www.londonstockexchange.com/indices/ftse-100/constituents/table",
  "updatedAt": "2026-03-10T10:02:40.201Z",
  "companies": [
    {
      "name": "PSN",
      "ticker": null,
      "price": 1316,
      "marketCap": 3924.34,
      "updatedAt": "2026-03-10T10:02:40.201Z"
    },
    {
      "name": "IAG",
      "ticker": null,
      "price": 377.8,
      "marketCap": 16325.21,
      "updatedAt": "2026-03-10T10:02:40.201Z"
    },
    {
      "name": "RR.",
      "ticker": null,
      "price": 1306.5,
      "marketCap": 104313.42,
      "updatedAt": "2026-03-10T10:02:40.201Z"
    },
    {
      "name": "ANTO",
      "ticker": null,
      "price": 3851,
      "marketCap": 36102.07,
      "updatedAt": "2026-03-10T10:02:40.201Z"
    },
    {
      "name": "FRES",
      "ticker": null,
      "price": 3688,
      "marketCap": 25850.23,
      "updatedAt": "2026-03-10T10:02:40.201Z"
    },
    {
      "name": "BARC",
      "ticker": null,
      "price": 417.5,
      "marketCap": 54818.41,
      "updatedAt": "2026-03-10T10:02:40.201Z"
    },
    {
      "name": "AAL",
      "ticker": null,
      "price": 3280,
      "marketCap": 36837.63,
      "updatedAt": "2026-03-10T10:02:40.201Z"
    },
    {
      "name": "STJ",
      "ticker": null,
      "price": 1337.5,
      "marketCap": 6736.28,
      "updatedAt": "2026-03-10T10:02:40.201Z"
    },
    {
      "name": "STAN",
      "ticker": null,
      "price": 1695,
      "marketCap": 36627.4,
      "updatedAt": "2026-03-10T10:02:40.201Z"
    },
    {
      "name": "AV.",
      "ticker": null,
      "price": 636.4,
      "marketCap": 18719.47,
      "updatedAt": "2026-03-10T10:02:40.201Z"
    },
    {
      "name": "PRU",
      "ticker": null,
      "price": 1106.5,
      "marketCap": 26966.46,
      "updatedAt": "2026-03-10T10:02:40.201Z"
    },
    {
      "name": "SGRO",
      "ticker": null,
      "price": 753.2,
      "marketCap": 9810.13,
      "updatedAt": "2026-03-10T10:02:40.201Z"
    },
    {
      "name": "SPX",
      "ticker": null,
      "price": 7330,
      "marketCap": 5204.9,
      "updatedAt": "2026-03-10T10:02:40.201Z"
    },
    {
      "name": "LLOY",
      "ticker": null,
      "price": 98.68,
      "marketCap": 56056.43,
      "updatedAt": "2026-03-10T10:02:40.201Z"
    },
    {
      "name": "EZJ",
      "ticker": null,
      "price": 410.1,
      "marketCap": 2997.93,
      "updatedAt": "2026-03-10T10:02:40.201Z"
    },
    {
      "name": "HLMA",
      "ticker": null,
      "price": 3934,
      "marketCap": 14426.52,
      "updatedAt": "2026-03-10T10:02:40.201Z"
    },
    {
      "name": "HIK",
      "ticker": null,
      "price": 1233,
      "marketCap": 2626.86,
      "updatedAt": "2026-03-10T10:02:40.201Z"
    },
    {
      "name": "JD.",
      "ticker": null,
      "price": 76.1,
      "marketCap": 3620.8,
      "updatedAt": "2026-03-10T10:02:40.201Z"
    },
    {
      "name": "SDLF",
      "ticker": null,
      "price": 714.5,
      "marketCap": 6948.79,
      "updatedAt": "2026-03-10T10:02:40.201Z"
    },
    {
      "name": "EDV",
      "ticker": null,
      "price": 4794,
      "marketCap": 11177.95,
      "updatedAt": "2026-03-10T10:02:40.201Z"
    },
    {
      "name": "LGEN",
      "ticker": null,
      "price": 258.5,
      "marketCap": 14238.63,
      "updatedAt": "2026-03-10T10:02:40.201Z"
    },
    {
      "name": "MNG",
      "ticker": null,
      "price": 307.2,
      "marketCap": 7156.36,
      "updatedAt": "2026-03-10T10:02:40.201Z"
    },
    {
      "name": "IHG",
      "ticker": null,
      "price": 132.7,
      "marketCap": 14446.14,
      "updatedAt": "2026-03-10T10:02:40.201Z"
    },
    {
      "name": "PCT",
      "ticker": null,
      "price": 500,
      "marketCap": 5407.52,
      "updatedAt": "2026-03-10T10:02:40.201Z"
    },
    {
      "name": "SMT",
      "ticker": null,
      "price": 1180,
      "marketCap": 12360.12,
      "updatedAt": "2026-03-10T10:02:40.201Z"
    },
    {
      "name": "BLND",
      "ticker": null,
      "price": 376.6,
      "marketCap": 3653.62,
      "updatedAt": "2026-03-10T10:02:40.201Z"
    },
    {
      "name": "ADM",
      "ticker": null,
      "price": 3214,
      "marketCap": 9556.71,
      "updatedAt": "2026-03-10T10:02:40.201Z"
    },
    {
      "name": "BRBY",
      "ticker": null,
      "price": 1092.5,
      "marketCap": 3830.16,
      "updatedAt": "2026-03-10T10:02:40.201Z"
    },
    {
      "name": "HSBA",
      "ticker": null,
      "price": 1288,
      "marketCap": 214862.25,
      "updatedAt": "2026-03-10T10:02:40.201Z"
    },
    {
      "name": "WEIR",
      "ticker": null,
      "price": 3014,
      "marketCap": 7601.44,
      "updatedAt": "2026-03-10T10:02:40.201Z"
    },
    {
      "name": "GAW",
      "ticker": null,
      "price": 17340,
      "marketCap": 5567.9,
      "updatedAt": "2026-03-10T10:02:40.201Z"
    },
    {
      "name": "GLEN",
      "ticker": null,
      "price": 521.3,
      "marketCap": 59474.78,
      "updatedAt": "2026-03-10T10:02:40.201Z"
    },
    {
      "name": "BBOX",
      "ticker": null,
      "price": 159.6,
      "marketCap": 4193.69,
      "updatedAt": "2026-03-10T10:02:40.201Z"
    },
    {
      "name": "ITRK",
      "ticker": null,
      "price": 3950,
      "marketCap": 5917.14,
      "updatedAt": "2026-03-10T10:02:40.201Z"
    },
    {
      "name": "BTRW",
      "ticker": null,
      "price": 310.8,
      "marketCap": 4296.34,
      "updatedAt": "2026-03-10T10:02:40.201Z"
    },
    {
      "name": "AAF",
      "ticker": null,
      "price": 346.4,
      "marketCap": 12291.59,
      "updatedAt": "2026-03-10T10:02:40.201Z"
    },
    {
      "name": "NWG",
      "ticker": null,
      "price": 591.4,
      "marketCap": 45900.16,
      "updatedAt": "2026-03-10T10:02:40.201Z"
    },
    {
      "name": "LMP",
      "ticker": null,
      "price": 201.8,
      "marketCap": 4609.1,
      "updatedAt": "2026-03-10T10:02:40.201Z"
    },
    {
      "name": "KGF",
      "ticker": null,
      "price": 322.9,
      "marketCap": 5318.24,
      "updatedAt": "2026-03-10T10:02:40.201Z"
    },
    {
      "name": "HSX",
      "ticker": null,
      "price": 1489,
      "marketCap": 4712.51,
      "updatedAt": "2026-03-10T10:02:40.201Z"
    },
    {
      "name": "IMI",
      "ticker": null,
      "price": 2794,
      "marketCap": 6733.47,
      "updatedAt": "2026-03-10T10:02:40.201Z"
    },
    {
      "name": "PSH",
      "ticker": null,
      "price": 4102,
      "marketCap": 7022.83,
      "updatedAt": "2026-03-10T10:02:40.201Z"
    },
    {
      "name": "DPLM",
      "ticker": null,
      "price": 5240,
      "marketCap": 6870.33,
      "updatedAt": "2026-03-10T10:02:40.201Z"
    },
    {
      "name": "ENT",
      "ticker": null,
      "price": 588.8,
      "marketCap": 3677.72,
      "updatedAt": "2026-03-10T10:02:40.201Z"
    },
    {
      "name": "CTEC",
      "ticker": null,
      "price": 244,
      "marketCap": 4660.37,
      "updatedAt": "2026-03-10T10:02:40.201Z"
    },
    {
      "name": "LAND",
      "ticker": null,
      "price": 601,
      "marketCap": 4377.1,
      "updatedAt": "2026-03-10T10:02:40.201Z"
    },
    {
      "name": "CRDA",
      "ticker": null,
      "price": 2780,
      "marketCap": 3795.29,
      "updatedAt": "2026-03-10T10:02:40.201Z"
    },
    {
      "name": "BKG",
      "ticker": null,
      "price": 3964,
      "marketCap": 3655.76,
      "updatedAt": "2026-03-10T10:02:40.201Z"
    },
    {
      "name": "DCC",
      "ticker": null,
      "price": 4796,
      "marketCap": 4006.34,
      "updatedAt": "2026-03-10T10:02:40.201Z"
    },
    {
      "name": "AZN",
      "ticker": null,
      "price": 14760,
      "marketCap": 223990.61,
      "updatedAt": "2026-03-10T10:02:40.201Z"
    },
    {
      "name": "INF",
      "ticker": null,
      "price": 792.4,
      "marketCap": 9939.5,
      "updatedAt": "2026-03-10T10:02:40.201Z"
    },
    {
      "name": "UU.",
      "ticker": null,
      "price": 1340.5,
      "marketCap": 8949.79,
      "updatedAt": "2026-03-10T10:02:40.201Z"
    },
    {
      "name": "CNA",
      "ticker": null,
      "price": 198.35,
      "marketCap": 8952.2,
      "updatedAt": "2026-03-10T10:02:40.201Z"
    },
    {
      "name": "BATS",
      "ticker": null,
      "price": 4396,
      "marketCap": 93688.67,
      "updatedAt": "2026-03-10T10:02:40.201Z"
    },
    {
      "name": "ICG",
      "ticker": null,
      "price": 1587,
      "marketCap": 4508.02,
      "updatedAt": "2026-03-10T10:02:40.201Z"
    },
    {
      "name": "SSE",
      "ticker": null,
      "price": 2683,
      "marketCap": 31892.14,
      "updatedAt": "2026-03-10T10:02:40.201Z"
    },
    {
      "name": "EXPN",
      "ticker": null,
      "price": 2827,
      "marketCap": 25209.55,
      "updatedAt": "2026-03-10T10:02:40.201Z"
    },
    {
      "name": "GSK",
      "ticker": null,
      "price": 2084,
      "marketCap": 83254.23,
      "updatedAt": "2026-03-10T10:02:40.201Z"
    },
    {
      "name": "HWDN",
      "ticker": null,
      "price": 859.5,
      "marketCap": 4549.48,
      "updatedAt": "2026-03-10T10:02:40.201Z"
    },
    {
      "name": "SMIN",
      "ticker": null,
      "price": 2610,
      "marketCap": 8018.91,
      "updatedAt": "2026-03-10T10:02:40.201Z"
    },
    {
      "name": "RMV",
      "ticker": null,
      "price": 461.5,
      "marketCap": 3452.57,
      "updatedAt": "2026-03-10T10:02:40.201Z"
    },
    {
      "name": "MRO",
      "ticker": null,
      "price": 534,
      "marketCap": 6561.65,
      "updatedAt": "2026-03-10T10:02:40.201Z"
    },
    {
      "name": "FCIT",
      "ticker": null,
      "price": 1236,
      "marketCap": 5752.8,
      "updatedAt": "2026-03-10T10:02:40.201Z"
    },
    {
      "name": "MNDI",
      "ticker": null,
      "price": 830,
      "marketCap": 3601.93,
      "updatedAt": "2026-03-10T10:02:40.201Z"
    },
    {
      "name": "VOD",
      "ticker": null,
      "price": 108.6,
      "marketCap": 24709.72,
      "updatedAt": "2026-03-10T10:02:40.201Z"
    },
    {
      "name": "SVT",
      "ticker": null,
      "price": 3126,
      "marketCap": 9261.47,
      "updatedAt": "2026-03-10T10:02:40.201Z"
    },
    {
      "name": "III",
      "ticker": null,
      "price": 2971,
      "marketCap": 29993.01,
      "updatedAt": "2026-03-10T10:02:40.201Z"
    },
    {
      "name": "NG.",
      "ticker": null,
      "price": 1352.5,
      "marketCap": 66242.69,
      "updatedAt": "2026-03-10T10:02:40.201Z"
    },
    {
      "name": "MKS",
      "ticker": null,
      "price": 358.4,
      "marketCap": 7294.4,
      "updatedAt": "2026-03-10T10:02:40.201Z"
    },
    {
      "name": "RIO",
      "ticker": null,
      "price": 6730,
      "marketCap": 83266.32,
      "updatedAt": "2026-03-10T10:02:40.201Z"
    },
    {
      "name": "WTB",
      "ticker": null,
      "price": 2473,
      "marketCap": 4091.22,
      "updatedAt": "2026-03-10T10:02:40.201Z"
    },
    {
      "name": "PSON",
      "ticker": null,
      "price": 992.2,
      "marketCap": 6161.27,
      "updatedAt": "2026-03-10T10:02:40.201Z"
    },
    {
      "name": "CCH",
      "ticker": null,
      "price": 4562,
      "marketCap": 16358.71,
      "updatedAt": "2026-03-10T10:02:40.201Z"
    },
    {
      "name": "ALW",
      "ticker": null,
      "price": 1244,
      "marketCap": 4650.74,
      "updatedAt": "2026-03-10T10:02:40.201Z"
    },
    {
      "name": "NXT",
      "ticker": null,
      "price": 12930,
      "marketCap": 15568.9,
      "updatedAt": "2026-03-10T10:02:40.201Z"
    },
    {
      "name": "SN.",
      "ticker": null,
      "price": 1266.5,
      "marketCap": 10640.61,
      "updatedAt": "2026-03-10T10:02:40.201Z"
    },
    {
      "name": "AUTO",
      "ticker": null,
      "price": 488.6,
      "marketCap": 4001.84,
      "updatedAt": "2026-03-10T10:02:40.201Z"
    },
    {
      "name": "BT.A",
      "ticker": null,
      "price": 205.8,
      "marketCap": 20314.05,
      "updatedAt": "2026-03-10T10:02:40.201Z"
    },
    {
      "name": "IMB",
      "ticker": null,
      "price": 3172,
      "marketCap": 24708.68,
      "updatedAt": "2026-03-10T10:02:40.201Z"
    },
    {
      "name": "RKT",
      "ticker": null,
      "price": 5520,
      "marketCap": 35292.32,
      "updatedAt": "2026-03-10T10:02:40.201Z"
    },
    {
      "name": "BAB",
      "ticker": null,
      "price": 1403,
      "marketCap": 6945.48,
      "updatedAt": "2026-03-10T10:02:40.201Z"
    },
    {
      "name": "MTLN",
      "ticker": null,
      "price": 35.9,
      "marketCap": 4406.82,
      "updatedAt": "2026-03-10T10:02:40.201Z"
    },
    {
      "name": "TSCO",
      "ticker": null,
      "price": 469.6,
      "marketCap": 29754.95,
      "updatedAt": "2026-03-10T10:02:40.201Z"
    },
    {
      "name": "REL",
      "ticker": null,
      "price": 2665,
      "marketCap": 47666.62,
      "updatedAt": "2026-03-10T10:02:40.201Z"
    },
    {
      "name": "CCEP",
      "ticker": null,
      "price": 7570,
      "marketCap": 33771.65,
      "updatedAt": "2026-03-10T10:02:40.201Z"
    },
    {
      "name": "LSEG",
      "ticker": null,
      "price": 8710,
      "marketCap": 43564.69,
      "updatedAt": "2026-03-10T10:02:40.201Z"
    },
    {
      "name": "ABF",
      "ticker": null,
      "price": 1855,
      "marketCap": 13084.98,
      "updatedAt": "2026-03-10T10:02:40.201Z"
    },
    {
      "name": "HLN",
      "ticker": null,
      "price": 375.6,
      "marketCap": 33308.45,
      "updatedAt": "2026-03-10T10:02:40.201Z"
    },
    {
      "name": "BNZL",
      "ticker": null,
      "price": 2238,
      "marketCap": 7223.43,
      "updatedAt": "2026-03-10T10:02:40.201Z"
    },
    {
      "name": "ULVR",
      "ticker": null,
      "price": 4921,
      "marketCap": 107138.97,
      "updatedAt": "2026-03-10T10:02:40.201Z"
    },
    {
      "name": "SGE",
      "ticker": null,
      "price": 844.8,
      "marketCap": 7883.86,
      "updatedAt": "2026-03-10T10:02:40.201Z"
    },
    {
      "name": "SDR",
      "ticker": null,
      "price": 585.5,
      "marketCap": 9422.66,
      "updatedAt": "2026-03-10T10:02:40.201Z"
    },
    {
      "name": "RTO",
      "ticker": null,
      "price": 459.2,
      "marketCap": 11592,
      "updatedAt": "2026-03-10T10:02:40.201Z"
    },
    {
      "name": "BEZ",
      "ticker": null,
      "price": 1288,
      "marketCap": 7721.69,
      "updatedAt": "2026-03-10T10:02:40.201Z"
    },
    {
      "name": "DGE",
      "ticker": null,
      "price": 1518.5,
      "marketCap": 33864.34,
      "updatedAt": "2026-03-10T10:02:40.201Z"
    },
    {
      "name": "CPG",
      "ticker": null,
      "price": 2278,
      "marketCap": 38820.83,
      "updatedAt": "2026-03-10T10:02:40.201Z"
    },
    {
      "name": "SBRY",
      "ticker": null,
      "price": 334.6,
      "marketCap": 7615.05,
      "updatedAt": "2026-03-10T10:02:40.201Z"
    },
    {
      "name": "BA.",
      "ticker": null,
      "price": 2233,
      "marketCap": 67731.54,
      "updatedAt": "2026-03-10T10:02:40.201Z"
    },
    {
      "name": "SHEL",
      "ticker": null,
      "price": 3151,
      "marketCap": 181415.26,
      "updatedAt": "2026-03-10T10:02:40.201Z"
    },
    {
      "name": "BP.",
      "ticker": null,
      "price": 494.8,
      "marketCap": 80098.32,
      "updatedAt": "2026-03-10T10:02:40.201Z"
    }
  ]
}
