{
  "source": "https://www.londonstockexchange.com/indices/ftse-100/constituents/table",
  "updatedAt": "2026-03-17T19:20:45.217Z",
  "companies": [
    {
      "name": "AAF",
      "ticker": null,
      "price": 378.4,
      "marketCap": 13084.68,
      "updatedAt": "2026-03-17T19:20:45.217Z"
    },
    {
      "name": "STAN",
      "ticker": null,
      "price": 1603.5,
      "marketCap": 34777.51,
      "updatedAt": "2026-03-17T19:20:45.217Z"
    },
    {
      "name": "III",
      "ticker": null,
      "price": 3020,
      "marketCap": 30074.99,
      "updatedAt": "2026-03-17T19:20:45.217Z"
    },
    {
      "name": "BT.A",
      "ticker": null,
      "price": 220,
      "marketCap": 21390.56,
      "updatedAt": "2026-03-17T19:20:45.217Z"
    },
    {
      "name": "ENT",
      "ticker": null,
      "price": 546.2,
      "marketCap": 3410.37,
      "updatedAt": "2026-03-17T19:20:45.217Z"
    },
    {
      "name": "HLN",
      "ticker": null,
      "price": 395,
      "marketCap": 34350.26,
      "updatedAt": "2026-03-17T19:20:45.217Z"
    },
    {
      "name": "IHG",
      "ticker": null,
      "price": 133.15,
      "marketCap": 14746.65,
      "updatedAt": "2026-03-17T19:20:45.217Z"
    },
    {
      "name": "SGRO",
      "ticker": null,
      "price": 759.2,
      "marketCap": 10059.18,
      "updatedAt": "2026-03-17T19:20:45.217Z"
    },
    {
      "name": "BP.",
      "ticker": null,
      "price": 551.9,
      "marketCap": 84857.1,
      "updatedAt": "2026-03-17T19:20:45.217Z"
    },
    {
      "name": "REL",
      "ticker": null,
      "price": 2632,
      "marketCap": 46433.74,
      "updatedAt": "2026-03-17T19:20:45.217Z"
    },
    {
      "name": "ITRK",
      "ticker": null,
      "price": 3722,
      "marketCap": 5618.51,
      "updatedAt": "2026-03-17T19:20:45.217Z"
    },
    {
      "name": "SMT",
      "ticker": null,
      "price": 1215.5,
      "marketCap": 12866.05,
      "updatedAt": "2026-03-17T19:20:45.217Z"
    },
    {
      "name": "LMP",
      "ticker": null,
      "price": 195.7,
      "marketCap": 4503.6,
      "updatedAt": "2026-03-17T19:20:45.217Z"
    },
    {
      "name": "HSX",
      "ticker": null,
      "price": 1551,
      "marketCap": 4939.83,
      "updatedAt": "2026-03-17T19:20:45.217Z"
    },
    {
      "name": "CNA",
      "ticker": null,
      "price": 212,
      "marketCap": 9592.3,
      "updatedAt": "2026-03-17T19:20:45.217Z"
    },
    {
      "name": "HIK",
      "ticker": null,
      "price": 1288,
      "marketCap": 2789.1,
      "updatedAt": "2026-03-17T19:20:45.217Z"
    },
    {
      "name": "SHEL",
      "ticker": null,
      "price": 3474,
      "marketCap": 193059.32,
      "updatedAt": "2026-03-17T19:20:45.217Z"
    },
    {
      "name": "MNG",
      "ticker": null,
      "price": 302.3,
      "marketCap": 7161.18,
      "updatedAt": "2026-03-17T19:20:45.217Z"
    },
    {
      "name": "SDLF",
      "ticker": null,
      "price": 699.5,
      "marketCap": 6923.63,
      "updatedAt": "2026-03-17T19:20:45.217Z"
    },
    {
      "name": "SGE",
      "ticker": null,
      "price": 859.6,
      "marketCap": 7904.75,
      "updatedAt": "2026-03-17T19:20:45.217Z"
    },
    {
      "name": "GLEN",
      "ticker": null,
      "price": 524.2,
      "marketCap": 60554.43,
      "updatedAt": "2026-03-17T19:20:45.217Z"
    },
    {
      "name": "UU.",
      "ticker": null,
      "price": 1372.5,
      "marketCap": 9219.13,
      "updatedAt": "2026-03-17T19:20:45.217Z"
    },
    {
      "name": "BNZL",
      "ticker": null,
      "price": 2304,
      "marketCap": 7359.6,
      "updatedAt": "2026-03-17T19:20:45.217Z"
    },
    {
      "name": "GAW",
      "ticker": null,
      "price": 17330,
      "marketCap": 5643.9,
      "updatedAt": "2026-03-17T19:20:45.217Z"
    },
    {
      "name": "BARC",
      "ticker": null,
      "price": 393.75,
      "marketCap": 53484.44,
      "updatedAt": "2026-03-17T19:20:45.217Z"
    },
    {
      "name": "STJ",
      "ticker": null,
      "price": 1311,
      "marketCap": 6784.51,
      "updatedAt": "2026-03-17T19:20:45.217Z"
    },
    {
      "name": "NWG",
      "ticker": null,
      "price": 581.6,
      "marketCap": 45814.54,
      "updatedAt": "2026-03-17T19:20:45.217Z"
    },
    {
      "name": "VOD",
      "ticker": null,
      "price": 111.15,
      "marketCap": 25333.26,
      "updatedAt": "2026-03-17T19:20:45.217Z"
    },
    {
      "name": "RR.",
      "ticker": null,
      "price": 1247,
      "marketCap": 103508.34,
      "updatedAt": "2026-03-17T19:20:45.217Z"
    },
    {
      "name": "LLOY",
      "ticker": null,
      "price": 96.2,
      "marketCap": 55801.59,
      "updatedAt": "2026-03-17T19:20:45.217Z"
    },
    {
      "name": "LGEN",
      "ticker": null,
      "price": 251.1,
      "marketCap": 14124.67,
      "updatedAt": "2026-03-17T19:20:45.217Z"
    },
    {
      "name": "BRBY",
      "ticker": null,
      "price": 1047,
      "marketCap": 3732.69,
      "updatedAt": "2026-03-17T19:20:45.217Z"
    },
    {
      "name": "MNDI",
      "ticker": null,
      "price": 834.8,
      "marketCap": 3639.89,
      "updatedAt": "2026-03-17T19:20:45.217Z"
    },
    {
      "name": "ANTO",
      "ticker": null,
      "price": 3562,
      "marketCap": 34712.01,
      "updatedAt": "2026-03-17T19:20:45.217Z"
    },
    {
      "name": "ADM",
      "ticker": null,
      "price": 3302,
      "marketCap": 9997.78,
      "updatedAt": "2026-03-17T19:20:45.217Z"
    },
    {
      "name": "PSON",
      "ticker": null,
      "price": 1002.5,
      "marketCap": 6215.4,
      "updatedAt": "2026-03-17T19:20:45.217Z"
    },
    {
      "name": "AUTO",
      "ticker": null,
      "price": 491.8,
      "marketCap": 4012.57,
      "updatedAt": "2026-03-17T19:20:45.217Z"
    },
    {
      "name": "WEIR",
      "ticker": null,
      "price": 2862,
      "marketCap": 7347.02,
      "updatedAt": "2026-03-17T19:20:45.217Z"
    },
    {
      "name": "BLND",
      "ticker": null,
      "price": 376.6,
      "marketCap": 3723.61,
      "updatedAt": "2026-03-17T19:20:45.217Z"
    },
    {
      "name": "BBOX",
      "ticker": null,
      "price": 153.3,
      "marketCap": 4096.42,
      "updatedAt": "2026-03-17T19:20:45.217Z"
    },
    {
      "name": "AV.",
      "ticker": null,
      "price": 647.6,
      "marketCap": 19587.1,
      "updatedAt": "2026-03-17T19:20:45.217Z"
    },
    {
      "name": "CRDA",
      "ticker": null,
      "price": 2652,
      "marketCap": 3664.03,
      "updatedAt": "2026-03-17T19:20:45.217Z"
    },
    {
      "name": "FCIT",
      "ticker": null,
      "price": 1239,
      "marketCap": 5799.7,
      "updatedAt": "2026-03-17T19:20:45.217Z"
    },
    {
      "name": "SPX",
      "ticker": null,
      "price": 6700,
      "marketCap": 4894.67,
      "updatedAt": "2026-03-17T19:20:45.217Z"
    },
    {
      "name": "BTRW",
      "ticker": null,
      "price": 288,
      "marketCap": 4046,
      "updatedAt": "2026-03-17T19:20:45.217Z"
    },
    {
      "name": "SVT",
      "ticker": null,
      "price": 3177,
      "marketCap": 9472.23,
      "updatedAt": "2026-03-17T19:20:45.217Z"
    },
    {
      "name": "LSEG",
      "ticker": null,
      "price": 8844,
      "marketCap": 43943.88,
      "updatedAt": "2026-03-17T19:20:45.217Z"
    },
    {
      "name": "RTO",
      "ticker": null,
      "price": 484.5,
      "marketCap": 12122.47,
      "updatedAt": "2026-03-17T19:20:45.217Z"
    },
    {
      "name": "SSE",
      "ticker": null,
      "price": 2743,
      "marketCap": 32934.6,
      "updatedAt": "2026-03-17T19:20:45.217Z"
    },
    {
      "name": "HSBA",
      "ticker": null,
      "price": 1207.2,
      "marketCap": 205381.52,
      "updatedAt": "2026-03-17T19:20:45.217Z"
    },
    {
      "name": "RIO",
      "ticker": null,
      "price": 6757,
      "marketCap": 84006.75,
      "updatedAt": "2026-03-17T19:20:45.217Z"
    },
    {
      "name": "EDV",
      "ticker": null,
      "price": 4564,
      "marketCap": 10983.53,
      "updatedAt": "2026-03-17T19:20:45.217Z"
    },
    {
      "name": "SN.",
      "ticker": null,
      "price": 1251.5,
      "marketCap": 10551.38,
      "updatedAt": "2026-03-17T19:20:45.217Z"
    },
    {
      "name": "EXPN",
      "ticker": null,
      "price": 2774,
      "marketCap": 24969.78,
      "updatedAt": "2026-03-17T19:20:45.217Z"
    },
    {
      "name": "PSN",
      "ticker": null,
      "price": 1201.5,
      "marketCap": 3824.91,
      "updatedAt": "2026-03-17T19:20:45.217Z"
    },
    {
      "name": "IAG",
      "ticker": null,
      "price": 355,
      "marketCap": 16041.95,
      "updatedAt": "2026-03-17T19:20:45.217Z"
    },
    {
      "name": "MRO",
      "ticker": null,
      "price": 511.6,
      "marketCap": 6348.55,
      "updatedAt": "2026-03-17T19:20:45.217Z"
    },
    {
      "name": "MTLN",
      "ticker": null,
      "price": 37.3,
      "marketCap": 4575.35,
      "updatedAt": "2026-03-17T19:20:45.217Z"
    },
    {
      "name": "ALW",
      "ticker": null,
      "price": 1240,
      "marketCap": 4658.72,
      "updatedAt": "2026-03-17T19:20:45.217Z"
    },
    {
      "name": "ICG",
      "ticker": null,
      "price": 1554,
      "marketCap": 4473.25,
      "updatedAt": "2026-03-17T19:20:45.217Z"
    },
    {
      "name": "AAL",
      "ticker": null,
      "price": 3135,
      "marketCap": 36708.05,
      "updatedAt": "2026-03-17T19:20:45.217Z"
    },
    {
      "name": "PCT",
      "ticker": null,
      "price": 500,
      "marketCap": 5543.47,
      "updatedAt": "2026-03-17T19:20:45.217Z"
    },
    {
      "name": "FRES",
      "ticker": null,
      "price": 3448,
      "marketCap": 25260.71,
      "updatedAt": "2026-03-17T19:20:45.217Z"
    },
    {
      "name": "IMI",
      "ticker": null,
      "price": 2684,
      "marketCap": 6580.63,
      "updatedAt": "2026-03-17T19:20:45.217Z"
    },
    {
      "name": "PRU",
      "ticker": null,
      "price": 1095,
      "marketCap": 27592.56,
      "updatedAt": "2026-03-17T19:20:45.217Z"
    },
    {
      "name": "SBRY",
      "ticker": null,
      "price": 351.8,
      "marketCap": 7927.44,
      "updatedAt": "2026-03-17T19:20:45.217Z"
    },
    {
      "name": "KGF",
      "ticker": null,
      "price": 313.9,
      "marketCap": 5281.06,
      "updatedAt": "2026-03-17T19:20:45.217Z"
    },
    {
      "name": "BAB",
      "ticker": null,
      "price": 1366,
      "marketCap": 6790.32,
      "updatedAt": "2026-03-17T19:20:45.217Z"
    },
    {
      "name": "WTB",
      "ticker": null,
      "price": 2391,
      "marketCap": 3993.93,
      "updatedAt": "2026-03-17T19:20:45.217Z"
    },
    {
      "name": "BA.",
      "ticker": null,
      "price": 2331,
      "marketCap": 69609.28,
      "updatedAt": "2026-03-17T19:20:45.217Z"
    },
    {
      "name": "ABF",
      "ticker": null,
      "price": 1880,
      "marketCap": 13268.22,
      "updatedAt": "2026-03-17T19:20:45.217Z"
    },
    {
      "name": "NG.",
      "ticker": null,
      "price": 1361,
      "marketCap": 67410.95,
      "updatedAt": "2026-03-17T19:20:45.217Z"
    },
    {
      "name": "SMIN",
      "ticker": null,
      "price": 2394,
      "marketCap": 7444.32,
      "updatedAt": "2026-03-17T19:20:45.217Z"
    },
    {
      "name": "DPLM",
      "ticker": null,
      "price": 5030,
      "marketCap": 6736.02,
      "updatedAt": "2026-03-17T19:20:45.217Z"
    },
    {
      "name": "AZN",
      "ticker": null,
      "price": 14402,
      "marketCap": 222780.86,
      "updatedAt": "2026-03-17T19:20:45.217Z"
    },
    {
      "name": "CCEP",
      "ticker": null,
      "price": 7640,
      "marketCap": 34220.74,
      "updatedAt": "2026-03-17T19:20:45.217Z"
    },
    {
      "name": "LAND",
      "ticker": null,
      "price": 593,
      "marketCap": 4410.63,
      "updatedAt": "2026-03-17T19:20:45.217Z"
    },
    {
      "name": "TSCO",
      "ticker": null,
      "price": 491.2,
      "marketCap": 31325.71,
      "updatedAt": "2026-03-17T19:20:45.217Z"
    },
    {
      "name": "DGE",
      "ticker": null,
      "price": 1451,
      "marketCap": 32283.56,
      "updatedAt": "2026-03-17T19:20:45.217Z"
    },
    {
      "name": "SDR",
      "ticker": null,
      "price": 572,
      "marketCap": 9213.27,
      "updatedAt": "2026-03-17T19:20:45.217Z"
    },
    {
      "name": "BEZ",
      "ticker": null,
      "price": 1290,
      "marketCap": 7733.68,
      "updatedAt": "2026-03-17T19:20:45.217Z"
    },
    {
      "name": "ULVR",
      "ticker": null,
      "price": 4880,
      "marketCap": 106647.36,
      "updatedAt": "2026-03-17T19:20:45.217Z"
    },
    {
      "name": "MKS",
      "ticker": null,
      "price": 359.7,
      "marketCap": 7430.67,
      "updatedAt": "2026-03-17T19:20:45.217Z"
    },
    {
      "name": "RMV",
      "ticker": null,
      "price": 451.1,
      "marketCap": 3435.89,
      "updatedAt": "2026-03-17T19:20:45.217Z"
    },
    {
      "name": "INF",
      "ticker": null,
      "price": 759.2,
      "marketCap": 9723.7,
      "updatedAt": "2026-03-17T19:20:45.217Z"
    },
    {
      "name": "PSH",
      "ticker": null,
      "price": 4120,
      "marketCap": 7237.34,
      "updatedAt": "2026-03-17T19:20:45.217Z"
    },
    {
      "name": "EZJ",
      "ticker": null,
      "price": 361.9,
      "marketCap": 2750.06,
      "updatedAt": "2026-03-17T19:20:45.217Z"
    },
    {
      "name": "CTEC",
      "ticker": null,
      "price": 233.2,
      "marketCap": 4570.44,
      "updatedAt": "2026-03-17T19:20:45.217Z"
    },
    {
      "name": "BKG",
      "ticker": null,
      "price": 3668,
      "marketCap": 3464.62,
      "updatedAt": "2026-03-17T19:20:45.217Z"
    },
    {
      "name": "CCH",
      "ticker": null,
      "price": 4538,
      "marketCap": 16555.01,
      "updatedAt": "2026-03-17T19:20:45.217Z"
    },
    {
      "name": "NXT",
      "ticker": null,
      "price": 12800,
      "marketCap": 15632.17,
      "updatedAt": "2026-03-17T19:20:45.217Z"
    },
    {
      "name": "BATS",
      "ticker": null,
      "price": 4544,
      "marketCap": 99378.11,
      "updatedAt": "2026-03-17T19:20:45.217Z"
    },
    {
      "name": "GSK",
      "ticker": null,
      "price": 2013,
      "marketCap": 82384.34,
      "updatedAt": "2026-03-17T19:20:45.217Z"
    },
    {
      "name": "DCC",
      "ticker": null,
      "price": 4594,
      "marketCap": 3949.96,
      "updatedAt": "2026-03-17T19:20:45.217Z"
    },
    {
      "name": "HWDN",
      "ticker": null,
      "price": 826,
      "marketCap": 4484.79,
      "updatedAt": "2026-03-17T19:20:45.217Z"
    },
    {
      "name": "JD.",
      "ticker": null,
      "price": 71,
      "marketCap": 3517.84,
      "updatedAt": "2026-03-17T19:20:45.217Z"
    },
    {
      "name": "RKT",
      "ticker": null,
      "price": 5430,
      "marketCap": 35344.2,
      "updatedAt": "2026-03-17T19:20:45.217Z"
    },
    {
      "name": "CPG",
      "ticker": null,
      "price": 2267,
      "marketCap": 38956.87,
      "updatedAt": "2026-03-17T19:20:45.217Z"
    },
    {
      "name": "HLMA",
      "ticker": null,
      "price": 3794,
      "marketCap": 14570.79,
      "updatedAt": "2026-03-17T19:20:45.217Z"
    },
    {
      "name": "IMB",
      "ticker": null,
      "price": 3215,
      "marketCap": 25538.46,
      "updatedAt": "2026-03-17T19:20:45.217Z"
    }
  ]
}
