{
  "source": "https://www.londonstockexchange.com/indices/ftse-100/constituents/table",
  "updatedAt": "2026-02-19T15:10:26.918Z",
  "companies": [
    {
      "name": "REL",
      "ticker": null,
      "price": 2333,
      "marketCap": 40440.74,
      "updatedAt": "2026-02-19T15:10:26.918Z"
    },
    {
      "name": "MNDI",
      "ticker": null,
      "price": 951.8,
      "marketCap": 4080.42,
      "updatedAt": "2026-02-19T15:10:26.918Z"
    },
    {
      "name": "BP.",
      "ticker": null,
      "price": 482.45,
      "marketCap": 73737.57,
      "updatedAt": "2026-02-19T15:10:26.918Z"
    },
    {
      "name": "BATS",
      "ticker": null,
      "price": 4431,
      "marketCap": 94499.4,
      "updatedAt": "2026-02-19T15:10:26.918Z"
    },
    {
      "name": "CCEP",
      "ticker": null,
      "price": 7870,
      "marketCap": 34804.56,
      "updatedAt": "2026-02-19T15:10:26.918Z"
    },
    {
      "name": "DGE",
      "ticker": null,
      "price": 1785,
      "marketCap": 39207.59,
      "updatedAt": "2026-02-19T15:10:26.918Z"
    },
    {
      "name": "LMP",
      "ticker": null,
      "price": 214.6,
      "marketCap": 4965.45,
      "updatedAt": "2026-02-19T15:10:26.918Z"
    },
    {
      "name": "CPG",
      "ticker": null,
      "price": 2206,
      "marketCap": 37069.39,
      "updatedAt": "2026-02-19T15:10:26.918Z"
    },
    {
      "name": "EXPN",
      "ticker": null,
      "price": 2581,
      "marketCap": 23283.6,
      "updatedAt": "2026-02-19T15:10:26.918Z"
    },
    {
      "name": "BEZ",
      "ticker": null,
      "price": 1223,
      "marketCap": 7260.06,
      "updatedAt": "2026-02-19T15:10:26.918Z"
    },
    {
      "name": "RTO",
      "ticker": null,
      "price": 463.6,
      "marketCap": 11614.73,
      "updatedAt": "2026-02-19T15:10:26.918Z"
    },
    {
      "name": "SGE",
      "ticker": null,
      "price": 807,
      "marketCap": 7556.84,
      "updatedAt": "2026-02-19T15:10:26.918Z"
    },
    {
      "name": "DCC",
      "ticker": null,
      "price": 5235,
      "marketCap": 4442,
      "updatedAt": "2026-02-19T15:10:26.918Z"
    },
    {
      "name": "SHEL",
      "ticker": null,
      "price": 2944.5,
      "marketCap": 166176.67,
      "updatedAt": "2026-02-19T15:10:26.918Z"
    },
    {
      "name": "MKS",
      "ticker": null,
      "price": 398.9,
      "marketCap": 8169.19,
      "updatedAt": "2026-02-19T15:10:26.918Z"
    },
    {
      "name": "ABF",
      "ticker": null,
      "price": 1975.5,
      "marketCap": 13961.05,
      "updatedAt": "2026-02-19T15:10:26.918Z"
    },
    {
      "name": "LSEG",
      "ticker": null,
      "price": 7820,
      "marketCap": 39368.1,
      "updatedAt": "2026-02-19T15:10:26.918Z"
    },
    {
      "name": "BT.A",
      "ticker": null,
      "price": 204,
      "marketCap": 20264.19,
      "updatedAt": "2026-02-19T15:10:26.918Z"
    },
    {
      "name": "RKT",
      "ticker": null,
      "price": 6488,
      "marketCap": 41741.34,
      "updatedAt": "2026-02-19T15:10:26.918Z"
    },
    {
      "name": "BLND",
      "ticker": null,
      "price": 413.8,
      "marketCap": 4129.52,
      "updatedAt": "2026-02-19T15:10:26.918Z"
    },
    {
      "name": "ALW",
      "ticker": null,
      "price": 1280,
      "marketCap": 4856.28,
      "updatedAt": "2026-02-19T15:10:26.918Z"
    },
    {
      "name": "SMIN",
      "ticker": null,
      "price": 2646,
      "marketCap": 8314.38,
      "updatedAt": "2026-02-19T15:10:26.918Z"
    },
    {
      "name": "IMI",
      "ticker": null,
      "price": 2878,
      "marketCap": 7099.01,
      "updatedAt": "2026-02-19T15:10:26.918Z"
    },
    {
      "name": "ULVR",
      "ticker": null,
      "price": 5335,
      "marketCap": 116187.18,
      "updatedAt": "2026-02-19T15:10:26.918Z"
    },
    {
      "name": "PSON",
      "ticker": null,
      "price": 928.8,
      "marketCap": 5864.37,
      "updatedAt": "2026-02-19T15:10:26.918Z"
    },
    {
      "name": "BA.",
      "ticker": null,
      "price": 2112,
      "marketCap": 63274.3,
      "updatedAt": "2026-02-19T15:10:26.918Z"
    },
    {
      "name": "ITRK",
      "ticker": null,
      "price": 4510,
      "marketCap": 6936.17,
      "updatedAt": "2026-02-19T15:10:26.918Z"
    },
    {
      "name": "AUTO",
      "ticker": null,
      "price": 471.9,
      "marketCap": 3934.13,
      "updatedAt": "2026-02-19T15:10:26.918Z"
    },
    {
      "name": "LGEN",
      "ticker": null,
      "price": 271.8,
      "marketCap": 15480.6,
      "updatedAt": "2026-02-19T15:10:26.918Z"
    },
    {
      "name": "SDR",
      "ticker": null,
      "price": 585.5,
      "marketCap": 9430.71,
      "updatedAt": "2026-02-19T15:10:26.918Z"
    },
    {
      "name": "HLN",
      "ticker": null,
      "price": 410.7,
      "marketCap": 36598.03,
      "updatedAt": "2026-02-19T15:10:26.918Z"
    },
    {
      "name": "SBRY",
      "ticker": null,
      "price": 354.4,
      "marketCap": 8026.8,
      "updatedAt": "2026-02-19T15:10:26.918Z"
    },
    {
      "name": "HWDN",
      "ticker": null,
      "price": 868.5,
      "marketCap": 4684.24,
      "updatedAt": "2026-02-19T15:10:26.918Z"
    },
    {
      "name": "CTEC",
      "ticker": null,
      "price": 230.6,
      "marketCap": 4511.8,
      "updatedAt": "2026-02-19T15:10:26.918Z"
    },
    {
      "name": "CRDA",
      "ticker": null,
      "price": 2967,
      "marketCap": 4148.57,
      "updatedAt": "2026-02-19T15:10:26.918Z"
    },
    {
      "name": "BAB",
      "ticker": null,
      "price": 1374,
      "marketCap": 6871.46,
      "updatedAt": "2026-02-19T15:10:26.918Z"
    },
    {
      "name": "LAND",
      "ticker": null,
      "price": 657,
      "marketCap": 4902.3,
      "updatedAt": "2026-02-19T15:10:26.918Z"
    },
    {
      "name": "MNG",
      "ticker": null,
      "price": 318.3,
      "marketCap": 7680.87,
      "updatedAt": "2026-02-19T15:10:26.918Z"
    },
    {
      "name": "EDV",
      "ticker": null,
      "price": 4694,
      "marketCap": 11341.98,
      "updatedAt": "2026-02-19T15:10:26.918Z"
    },
    {
      "name": "PCT",
      "ticker": null,
      "price": 506,
      "marketCap": 5658.64,
      "updatedAt": "2026-02-19T15:10:26.918Z"
    },
    {
      "name": "CCH",
      "ticker": null,
      "price": 4726,
      "marketCap": 17216.63,
      "updatedAt": "2026-02-19T15:10:26.918Z"
    },
    {
      "name": "GAW",
      "ticker": null,
      "price": 16980,
      "marketCap": 5624.03,
      "updatedAt": "2026-02-19T15:10:26.918Z"
    },
    {
      "name": "III",
      "ticker": null,
      "price": 3412,
      "marketCap": 35054.97,
      "updatedAt": "2026-02-19T15:10:26.918Z"
    },
    {
      "name": "SGRO",
      "ticker": null,
      "price": 791,
      "marketCap": 10735.92,
      "updatedAt": "2026-02-19T15:10:26.918Z"
    },
    {
      "name": "KGF",
      "ticker": null,
      "price": 360,
      "marketCap": 6116.15,
      "updatedAt": "2026-02-19T15:10:26.918Z"
    },
    {
      "name": "BNZL",
      "ticker": null,
      "price": 2120,
      "marketCap": 6899.22,
      "updatedAt": "2026-02-19T15:10:26.918Z"
    },
    {
      "name": "WEIR",
      "ticker": null,
      "price": 3446,
      "marketCap": 8982.58,
      "updatedAt": "2026-02-19T15:10:26.918Z"
    },
    {
      "name": "VOD",
      "ticker": null,
      "price": 115.6,
      "marketCap": 26962.95,
      "updatedAt": "2026-02-19T15:10:26.918Z"
    },
    {
      "name": "TSCO",
      "ticker": null,
      "price": 492,
      "marketCap": 31555.57,
      "updatedAt": "2026-02-19T15:10:26.918Z"
    },
    {
      "name": "DPLM",
      "ticker": null,
      "price": 5595,
      "marketCap": 7548.64,
      "updatedAt": "2026-02-19T15:10:26.918Z"
    },
    {
      "name": "JD.",
      "ticker": null,
      "price": 78.98,
      "marketCap": 3924.42,
      "updatedAt": "2026-02-19T15:10:26.918Z"
    },
    {
      "name": "SMT",
      "ticker": null,
      "price": 1251,
      "marketCap": 13598.68,
      "updatedAt": "2026-02-19T15:10:26.918Z"
    },
    {
      "name": "INF",
      "ticker": null,
      "price": 821.2,
      "marketCap": 10588.53,
      "updatedAt": "2026-02-19T15:10:26.918Z"
    },
    {
      "name": "NXT",
      "ticker": null,
      "price": 12950,
      "marketCap": 15879.92,
      "updatedAt": "2026-02-19T15:10:26.918Z"
    },
    {
      "name": "HSX",
      "ticker": null,
      "price": 1447,
      "marketCap": 4726.67,
      "updatedAt": "2026-02-19T15:10:26.918Z"
    },
    {
      "name": "STJ",
      "ticker": null,
      "price": 1263.5,
      "marketCap": 6697.65,
      "updatedAt": "2026-02-19T15:10:26.918Z"
    },
    {
      "name": "ADM",
      "ticker": null,
      "price": 2826,
      "marketCap": 8705.18,
      "updatedAt": "2026-02-19T15:10:26.918Z"
    },
    {
      "name": "AV.",
      "ticker": null,
      "price": 639.4,
      "marketCap": 19667.37,
      "updatedAt": "2026-02-19T15:10:26.918Z"
    },
    {
      "name": "SN.",
      "ticker": null,
      "price": 1326,
      "marketCap": 11336.49,
      "updatedAt": "2026-02-19T15:10:26.918Z"
    },
    {
      "name": "RMV",
      "ticker": null,
      "price": 427.4,
      "marketCap": 3281.16,
      "updatedAt": "2026-02-19T15:10:26.918Z"
    },
    {
      "name": "AHT",
      "ticker": null,
      "price": 5070,
      "marketCap": 21159.42,
      "updatedAt": "2026-02-19T15:10:26.918Z"
    },
    {
      "name": "PHNX",
      "ticker": null,
      "price": 756,
      "marketCap": 7662.83,
      "updatedAt": "2026-02-19T15:10:26.918Z"
    },
    {
      "name": "FCIT",
      "ticker": null,
      "price": 1276,
      "marketCap": 6092.16,
      "updatedAt": "2026-02-19T15:10:26.918Z"
    },
    {
      "name": "BKG",
      "ticker": null,
      "price": 4290,
      "marketCap": 4091.38,
      "updatedAt": "2026-02-19T15:10:26.918Z"
    },
    {
      "name": "PSH",
      "ticker": null,
      "price": 4448,
      "marketCap": 7884.21,
      "updatedAt": "2026-02-19T15:10:26.918Z"
    },
    {
      "name": "HLMA",
      "ticker": null,
      "price": 3926,
      "marketCap": 15041.55,
      "updatedAt": "2026-02-19T15:10:26.918Z"
    },
    {
      "name": "NG.",
      "ticker": null,
      "price": 1336,
      "marketCap": 67037.86,
      "updatedAt": "2026-02-19T15:10:26.918Z"
    },
    {
      "name": "SPX",
      "ticker": null,
      "price": 7800,
      "marketCap": 5809.86,
      "updatedAt": "2026-02-19T15:10:26.918Z"
    },
    {
      "name": "RR.",
      "ticker": null,
      "price": 1311.5,
      "marketCap": 111640.29,
      "updatedAt": "2026-02-19T15:10:26.918Z"
    },
    {
      "name": "IMB",
      "ticker": null,
      "price": 3219,
      "marketCap": 25724.17,
      "updatedAt": "2026-02-19T15:10:26.918Z"
    },
    {
      "name": "ICG",
      "ticker": null,
      "price": 1735,
      "marketCap": 5094.92,
      "updatedAt": "2026-02-19T15:10:26.918Z"
    },
    {
      "name": "PRU",
      "ticker": null,
      "price": 1111.5,
      "marketCap": 28537.89,
      "updatedAt": "2026-02-19T15:10:26.918Z"
    },
    {
      "name": "HSBA",
      "ticker": null,
      "price": 1281.4,
      "marketCap": 222900.26,
      "updatedAt": "2026-02-19T15:10:26.918Z"
    },
    {
      "name": "SVT",
      "ticker": null,
      "price": 3116,
      "marketCap": 9508.36,
      "updatedAt": "2026-02-19T15:10:26.918Z"
    },
    {
      "name": "PSN",
      "ticker": null,
      "price": 1522,
      "marketCap": 4950.19,
      "updatedAt": "2026-02-19T15:10:26.918Z"
    },
    {
      "name": "UU.",
      "ticker": null,
      "price": 1330,
      "marketCap": 9205.49,
      "updatedAt": "2026-02-19T15:10:26.918Z"
    },
    {
      "name": "STAN",
      "ticker": null,
      "price": 1779.5,
      "marketCap": 40783.28,
      "updatedAt": "2026-02-19T15:10:26.918Z"
    },
    {
      "name": "FRES",
      "ticker": null,
      "price": 3846,
      "marketCap": 28827.28,
      "updatedAt": "2026-02-19T15:10:26.918Z"
    },
    {
      "name": "ENT",
      "ticker": null,
      "price": 578,
      "marketCap": 3769.82,
      "updatedAt": "2026-02-19T15:10:26.918Z"
    },
    {
      "name": "GSK",
      "ticker": null,
      "price": 2223,
      "marketCap": 92439.86,
      "updatedAt": "2026-02-19T15:10:26.918Z"
    },
    {
      "name": "AAF",
      "ticker": null,
      "price": 350.4,
      "marketCap": 13037.89,
      "updatedAt": "2026-02-19T15:10:26.918Z"
    },
    {
      "name": "GLEN",
      "ticker": null,
      "price": 497.45,
      "marketCap": 59580.4,
      "updatedAt": "2026-02-19T15:10:26.918Z"
    },
    {
      "name": "BRBY",
      "ticker": null,
      "price": 1156,
      "marketCap": 4263.34,
      "updatedAt": "2026-02-19T15:10:26.918Z"
    },
    {
      "name": "LLOY",
      "ticker": null,
      "price": 102.35,
      "marketCap": 61590.02,
      "updatedAt": "2026-02-19T15:10:26.918Z"
    },
    {
      "name": "BTRW",
      "ticker": null,
      "price": 377.5,
      "marketCap": 5488.18,
      "updatedAt": "2026-02-19T15:10:26.918Z"
    },
    {
      "name": "IHG",
      "ticker": null,
      "price": 141.8,
      "marketCap": 16226.4,
      "updatedAt": "2026-02-19T15:10:26.918Z"
    },
    {
      "name": "AZN",
      "ticker": null,
      "price": 15190,
      "marketCap": 241047.81,
      "updatedAt": "2026-02-19T15:10:26.918Z"
    },
    {
      "name": "NWG",
      "ticker": null,
      "price": 615.6,
      "marketCap": 50277.28,
      "updatedAt": "2026-02-19T15:10:26.918Z"
    },
    {
      "name": "MRO",
      "ticker": null,
      "price": 665.8,
      "marketCap": 8545.5,
      "updatedAt": "2026-02-19T15:10:26.918Z"
    },
    {
      "name": "MTLN",
      "ticker": null,
      "price": 35.25,
      "marketCap": 4512.43,
      "updatedAt": "2026-02-19T15:10:26.918Z"
    },
    {
      "name": "WTB",
      "ticker": null,
      "price": 2687,
      "marketCap": 4632.56,
      "updatedAt": "2026-02-19T15:10:26.918Z"
    },
    {
      "name": "IAG",
      "ticker": null,
      "price": 430.4,
      "marketCap": 20187,
      "updatedAt": "2026-02-19T15:10:26.918Z"
    },
    {
      "name": "BARC",
      "ticker": null,
      "price": 470.95,
      "marketCap": 67117.11,
      "updatedAt": "2026-02-19T15:10:26.918Z"
    },
    {
      "name": "SSE",
      "ticker": null,
      "price": 2519,
      "marketCap": 31564.24,
      "updatedAt": "2026-02-19T15:10:26.918Z"
    },
    {
      "name": "ANTO",
      "ticker": null,
      "price": 3865,
      "marketCap": 39434.27,
      "updatedAt": "2026-02-19T15:10:26.918Z"
    },
    {
      "name": "AAL",
      "ticker": null,
      "price": 3523,
      "marketCap": 43128.42,
      "updatedAt": "2026-02-19T15:10:26.918Z"
    },
    {
      "name": "EZJ",
      "ticker": null,
      "price": 472.5,
      "marketCap": 3731.68,
      "updatedAt": "2026-02-19T15:10:26.918Z"
    },
    {
      "name": "CNA",
      "ticker": null,
      "price": 187.15,
      "marketCap": 9025.53,
      "updatedAt": "2026-02-19T15:10:26.918Z"
    },
    {
      "name": "RIO",
      "ticker": null,
      "price": 7053,
      "marketCap": 92693.19,
      "updatedAt": "2026-02-19T15:10:26.918Z"
    }
  ]
}
